Metadata-Version: 2.1
Name: shopschedule
Version: 0.0.0
Summary: UNKNOWN
Home-page: UNKNOWN
Author: hufuture
Author-email: 1623025938@163.com
License: UNKNOWN
Platform: UNKNOWN
Classifier: Programming Language :: Python :: 3
